toptle.py
toptle-0.1.1.dist-info/licenses/LICENSE
toptle-0.1.1.dist-info/METADATA
toptle-0.1.1.dist-info/WHEEL
toptle-0.1.1.dist-info/entry_points.txt
toptle-0.1.1.dist-info/top_level.txt
toptle-0.1.1.dist-info/RECORD
