Metadata-Version: 2.4
Name: toptle
Version: 0.1.1
Summary: A process monitor in your terminal title
Author-email: Yves Parès <yves.pares@gmail.com>
License: MIT
Project-URL: Homepage, https://github.com/YPares/toptle
Project-URL: Issues, https://github.com/YPares/toptle/issues
Project-URL: Repository, https://github.com/YPares/toptle
Keywords: monitor,process,pty,terminal,title
Classifier: Development Status :: 4 - Beta
Classifier: Environment :: Console
Classifier: Intended Audience :: Developers
Classifier: License :: OSI Approved :: MIT License
Classifier: Operating System :: MacOS
Classifier: Operating System :: POSIX :: Linux
Classifier: Programming Language :: Python :: 3
Classifier: Programming Language :: Python :: 3.8
Classifier: Programming Language :: Python :: 3.9
Classifier: Programming Language :: Python :: 3.10
Classifier: Programming Language :: Python :: 3.11
Classifier: Programming Language :: Python :: 3.12
Classifier: Topic :: System :: Monitoring
Classifier: Topic :: Terminals
Classifier: Topic :: Utilities
Requires-Python: >=3.8
License-File: LICENSE
Requires-Dist: psutil>=5.8.0
Dynamic: license-file
